kafkit/__init__.py
kafkit/httputils.py
kafkit/py.typed
kafkit/ssl.py
kafkit/registry/__init__.py
kafkit/registry/aiohttp.py
kafkit/registry/errors.py
kafkit/registry/httpx.py
kafkit/registry/manager.py
kafkit/registry/sansio.py
kafkit/registry/serializer.py
kafkit-0.3.1.dist-info/licenses/LICENSE
kafkit-0.3.1.dist-info/METADATA
kafkit-0.3.1.dist-info/WHEEL
kafkit-0.3.1.dist-info/top_level.txt
kafkit-0.3.1.dist-info/RECORD
