Metadata-Version: 2.4
Name: kafkit
Version: 0.3.1
Summary: Kafkit helps you write Kafka producers and consumers in Python with asyncio.
Author-email: "Association of Universities for Research in Astronomy, Inc. (AURA)" <sqre-admin@lists.lsst.org>
License-Expression: MIT
Project-URL: Homepage, https://kafkit.lsst.io
Project-URL: Source, https://github.com/lsst-sqre/kafkit
Keywords: rubin,lsst
Classifier: Development Status :: 4 - Beta
Classifier: Programming Language :: Python
Classifier: Programming Language :: Python :: 3
Classifier: Programming Language :: Python :: 3.11
Classifier: Programming Language :: Python :: 3.12
Classifier: Programming Language :: Python :: 3.13
Classifier: Intended Audience :: Developers
Classifier: Natural Language :: English
Classifier: Operating System :: POSIX
Classifier: Typing :: Typed
Requires-Python: >=3.11
License-File: LICENSE
Requires-Dist: uritemplate
Requires-Dist: fastavro
Provides-Extra: aiohttp
Requires-Dist: aiohttp; extra == "aiohttp"
Provides-Extra: httpx
Requires-Dist: httpx; extra == "httpx"
Provides-Extra: dev
Requires-Dist: coverage[toml]; extra == "dev"
Requires-Dist: pytest; extra == "dev"
Requires-Dist: pytest-asyncio; extra == "dev"
Requires-Dist: pre-commit; extra == "dev"
Requires-Dist: mypy; extra == "dev"
Requires-Dist: sphinx; extra == "dev"
Requires-Dist: documenteer[guide]; extra == "dev"
Dynamic: license-file
